ai_coder/__init__.py
ai_coder/cli.py
ai_coder/main.py
ai_coder/server.py
ai_coder/tools/files.py
ai_coder/tools/ollama.py
ai_coder/tools/shell.py
ai_coder/utils/__init__.py
ai_coder/utils/fsx.py
ai_coder/utils/logger.py
codedev-3.0.0.data/data/share/codedev/config/default.yaml
codedev-3.0.0.dist-info/licenses/LICENSE
codedev-3.0.0.dist-info/METADATA
codedev-3.0.0.dist-info/WHEEL
codedev-3.0.0.dist-info/entry_points.txt
codedev-3.0.0.dist-info/top_level.txt
codedev-3.0.0.dist-info/RECORD
