Metadata-Version: 2.4
Name: codedev
Version: 3.0.0
Summary: Advanced AI Coding Assistant with Terminal Integration
Home-page: https://ashokumar.in
Author: Ashok Kumar
Author-email: Ashok Kumar <contact@ashokumar.in>
License: MIT
Project-URL: Homepage, https://ashokumar.in
Project-URL: Repository, https://github.com/ashokumar06/codedev
Project-URL: Bug Reports, https://github.com/ashokumar06/codedev/issues
Project-URL: Documentation, https://ashokumar.in/codedev
Keywords: ai,coding,assistant,terminal,automation,ollama,code-generation
Classifier: Development Status :: 5 - Production/Stable
Classifier: Intended Audience :: Developers
Classifier: Intended Audience :: System Administrators
Classifier: License :: OSI Approved :: MIT License
Classifier: Operating System :: OS Independent
Classifier: Programming Language :: Python :: 3
Classifier: Programming Language :: Python :: 3.8
Classifier: Programming Language :: Python :: 3.9
Classifier: Programming Language :: Python :: 3.10
Classifier: Programming Language :: Python :: 3.11
Classifier: Programming Language :: Python :: 3.12
Classifier: Programming Language :: Python :: 3.13
Classifier: Topic :: Software Development :: Code Generators
Classifier: Topic :: Software Development :: Libraries :: Python Modules
Classifier: Topic :: System :: Systems Administration
Classifier: Topic :: Utilities
Classifier: Environment :: Console
Requires-Python: >=3.8
License-File: LICENSE
Requires-Dist: requests>=2.31.0
Requires-Dist: prompt-toolkit>=3.0.39
Requires-Dist: rich>=13.4.2
Requires-Dist: pyyaml>=6.0.1
Requires-Dist: click>=8.1.6
Requires-Dist: colorama>=0.4.6
Requires-Dist: watchdog>=3.0.0
Requires-Dist: jsonschema>=4.18.0
Requires-Dist: httpx>=0.24.0
Requires-Dist: anyio>=4.0.0
Requires-Dist: python-dotenv>=1.0.0
Dynamic: author
Dynamic: home-page
Dynamic: license-file
Dynamic: requires-python
